salesforce_text_formatter/__init__.py
salesforce_text_formatter/format.py
Text_Formatter_sf-1.0.3.dist-info/LICENSE
Text_Formatter_sf-1.0.3.dist-info/METADATA
Text_Formatter_sf-1.0.3.dist-info/WHEEL
Text_Formatter_sf-1.0.3.dist-info/top_level.txt
Text_Formatter_sf-1.0.3.dist-info/RECORD
