Metadata-Version: 2.1
Name: Text-Formatter-sf
Version: 1.0.3
Summary: A text formatting package for salesforce data engineers
Author-email: Daniel Lambert <daniel.lambert@deliveryhero.com>
License: The MIT License (MIT)
Project-URL: Homepage, https://github.com/daniellambertdh/sf-text-formatter
Classifier: Programming Language :: Python :: 3
Classifier: License :: OSI Approved :: MIT License
Classifier: Operating System :: OS Independent
Requires-Python: >=3.7
License-File: LICENSE
Requires-Dist: wordninja
